__init__.py
PondLibrary/PondLibrary.py
PondLibrary/__init__.py
pond_library-0.0.2.dist-info/LICENSE
pond_library-0.0.2.dist-info/METADATA
pond_library-0.0.2.dist-info/WHEEL
pond_library-0.0.2.dist-info/top_level.txt
pond_library-0.0.2.dist-info/RECORD
